yfs/__init__.py
YahooFinanceScraping-0.0.3.dist-info/LICENSE.txt
YahooFinanceScraping-0.0.3.dist-info/METADATA
YahooFinanceScraping-0.0.3.dist-info/WHEEL
YahooFinanceScraping-0.0.3.dist-info/top_level.txt
YahooFinanceScraping-0.0.3.dist-info/RECORD
