Metadata-Version: 2.1
Name: YahooFinanceScraping
Version: 0.0.3
Summary: Library to scraping from yahoo finance page quote data..
Home-page: https://github.com/juliansantosinfo/yahoofinancescraping
Author: Julian de Almeida Santos
Author-email: julian.santos.info@gmail.com
License: MIT
Project-URL: Source, https://github.com/juliansantosinfo/yahoofinancescraping
Keywords: yahoo,finance
Platform: UNKNOWN
Classifier: Development Status :: 5 - Production/Stable
Classifier: Environment :: Console
Classifier: Environment :: MacOS X
Classifier: Environment :: Web Environment
Classifier: Environment :: X11 Applications
Classifier: Intended Audience :: Developers
Classifier: License :: OSI Approved :: MIT License
Classifier: Operating System :: OS Independent
Classifier: Programming Language :: Python
Classifier: Programming Language :: Python :: 3
Classifier: Programming Language :: Python :: 3 :: Only
Classifier: Programming Language :: Python :: 3.8
Classifier: Programming Language :: Python :: 3.9
Classifier: Topic :: Database
Classifier: Topic :: Internet
Classifier: Topic :: Software Development
Requires-Python: >=3.8
Requires-Dist: requests
Requires-Dist: beautifulsoup4
